{
  "generated_at": "2026-04-14T06:00:15.025709",
  "version": "3.92",
  "scan_hours": 72,
  "retention_days": 8,
  "activities": [
    {
      "activity_id": "i137662552",
      "date": "2026-04-06",
      "type": "VirtualRide",
      "name": "MyWhoosh - Aerobic 12's #1",
      "interval_summary": [
        "1x 2m57s 183w",
        "3x 11m56s 151w"
      ],
      "intervals": [
        {
          "type": "RECOVERY",
          "duration_secs": 723,
          "avg_power": 125,
          "max_power": 183,
          "avg_cadence": 90.24066,
          "zone": 2,
          "training_load": 10.225263
        },
        {
          "type": "WORK",
          "label": "177s@183w97rpm",
          "duration_secs": 177,
          "avg_power": 183,
          "max_power": 185,
          "avg_cadence": 96.644066,
          "zone": 4,
          "training_load": 4.225794
        },
        {
          "type": "RECOVERY",
          "duration_secs": 61,
          "avg_power": 82,
          "max_power": 169,
          "avg_cadence": 82.196724,
          "zone": 1,
          "training_load": 0.66189235
        },
        {
          "type": "WORK",
          "label": "716s@151w94rpm",
          "duration_secs": 720,
          "avg_power": 150,
          "max_power": 160,
          "avg_cadence": 93.35555,
          "zone": 3,
          "training_load": 12.207031
        },
        {
          "type": "RECOVERY",
          "duration_secs": 181,
          "avg_power": 102,
          "max_power": 151,
          "avg_cadence": 89.17127,
          "zone": 1,
          "training_load": 1.5908203
        },
        {
          "type": "WORK",
          "label": "716s@151w94rpm",
          "duration_secs": 708,
          "avg_power": 153,
          "max_power": 157,
          "avg_cadence": 95.34039,
          "zone": 3,
          "training_load": 12.488525
        },
        {
          "type": "RECOVERY",
          "duration_secs": 192,
          "avg_power": 104,
          "max_power": 155,
          "avg_cadence": 79.864586,
          "zone": 1,
          "training_load": 1.8148148
        },
        {
          "type": "WORK",
          "label": "716s@151w94rpm",
          "duration_secs": 719,
          "avg_power": 151,
          "max_power": 159,
          "avg_cadence": 92.99444,
          "zone": 3,
          "training_load": 12.353153
        },
        {
          "type": "RECOVERY",
          "duration_secs": 335,
          "avg_power": 89,
          "max_power": 151,
          "avg_cadence": 77.82985,
          "zone": 1,
          "training_load": 2.626275
        }
      ]
    },
    {
      "activity_id": "i137939724",
      "date": "2026-04-07",
      "type": "Run",
      "name": "Afternoon Run",
      "interval_summary": [
        "1x 6m12s 111bpm",
        "6x 5m57s 130bpm",
        "1x 1m56s 130bpm"
      ],
      "intervals": [
        {
          "type": "WORK",
          "label": "372s@111bpm81rpm",
          "duration_secs": 372,
          "avg_hr": 111,
          "max_hr": 120,
          "avg_cadence": 81.18801,
          "zone": 1
        },
        {
          "type": "WORK",
          "label": "357s@130bpm81rpm",
          "duration_secs": 342,
          "avg_hr": 127,
          "max_hr": 147,
          "avg_cadence": 82.17544,
          "zone": 1
        },
        {
          "type": "WORK",
          "label": "357s@130bpm81rpm",
          "duration_secs": 376,
          "avg_hr": 128,
          "max_hr": 139,
          "avg_cadence": 77.72872,
          "zone": 1
        },
        {
          "type": "WORK",
          "label": "357s@130bpm81rpm",
          "duration_secs": 346,
          "avg_hr": 127,
          "max_hr": 136,
          "avg_cadence": 82.361275,
          "zone": 1
        },
        {
          "type": "WORK",
          "label": "357s@130bpm81rpm",
          "duration_secs": 364,
          "avg_hr": 129,
          "max_hr": 143,
          "avg_cadence": 81.62363,
          "zone": 1
        },
        {
          "type": "WORK",
          "label": "357s@130bpm81rpm",
          "duration_secs": 349,
          "avg_hr": 131,
          "max_hr": 136,
          "avg_cadence": 82.126076,
          "zone": 1
        },
        {
          "type": "WORK",
          "label": "357s@130bpm81rpm",
          "duration_secs": 364,
          "avg_hr": 135,
          "max_hr": 146,
          "avg_cadence": 80.94505,
          "zone": 1
        },
        {
          "type": "WORK",
          "label": "116s@130bpm81rpm",
          "duration_secs": 116,
          "avg_hr": 130,
          "max_hr": 134,
          "avg_cadence": 80.80173,
          "zone": 1
        },
        {
          "type": "RECOVERY",
          "duration_secs": 1,
          "avg_hr": 131,
          "max_hr": 131,
          "zone": 1
        }
      ]
    },
    {
      "activity_id": "i138237135",
      "date": "2026-04-08",
      "type": "Ride",
      "name": "Afternoon Ride",
      "interval_summary": [
        "1x 12m40s 99bpm",
        "10x 10m24s 128bpm",
        "1x 13m1s 136bpm",
        "1x 8m3s 116bpm"
      ],
      "intervals": [
        {
          "type": "WORK",
          "label": "760s@99bpm",
          "duration_secs": 760,
          "avg_hr": 99,
          "max_hr": 124,
          "zone": 1
        },
        {
          "type": "WORK",
          "label": "624s@128bpm",
          "duration_secs": 704,
          "avg_hr": 114,
          "max_hr": 142,
          "zone": 1
        },
        {
          "type": "WORK",
          "label": "624s@128bpm",
          "duration_secs": 681,
          "avg_hr": 127,
          "max_hr": 145,
          "zone": 1
        },
        {
          "type": "WORK",
          "label": "781s@136bpm",
          "duration_secs": 781,
          "avg_hr": 136,
          "max_hr": 159,
          "zone": 1
        },
        {
          "type": "WORK",
          "label": "624s@128bpm",
          "duration_secs": 560,
          "avg_hr": 132,
          "max_hr": 170,
          "zone": 1
        },
        {
          "type": "WORK",
          "label": "624s@128bpm",
          "duration_secs": 577,
          "avg_hr": 136,
          "max_hr": 161,
          "zone": 1
        },
        {
          "type": "WORK",
          "label": "624s@128bpm",
          "duration_secs": 585,
          "avg_hr": 135,
          "max_hr": 155,
          "zone": 1
        },
        {
          "type": "WORK",
          "label": "624s@128bpm",
          "duration_secs": 639,
          "avg_hr": 129,
          "max_hr": 156,
          "zone": 1
        },
        {
          "type": "WORK",
          "label": "624s@128bpm",
          "duration_secs": 613,
          "avg_hr": 135,
          "max_hr": 156,
          "zone": 1
        },
        {
          "type": "WORK",
          "label": "624s@128bpm",
          "duration_secs": 617,
          "avg_hr": 130,
          "max_hr": 155,
          "zone": 1
        },
        {
          "type": "WORK",
          "label": "624s@128bpm",
          "duration_secs": 584,
          "avg_hr": 117,
          "max_hr": 139,
          "zone": 1
        },
        {
          "type": "WORK",
          "label": "624s@128bpm",
          "duration_secs": 679,
          "avg_hr": 124,
          "max_hr": 145,
          "zone": 1
        },
        {
          "type": "WORK",
          "label": "483s@116bpm",
          "duration_secs": 483,
          "avg_hr": 116,
          "max_hr": 132,
          "zone": 1
        },
        {
          "type": "RECOVERY",
          "duration_secs": 1,
          "avg_hr": 104,
          "max_hr": 104,
          "zone": 1
        }
      ]
    },
    {
      "activity_id": "i138500599",
      "date": "2026-04-09",
      "type": "VirtualRide",
      "name": "Sweet Spot Power Test",
      "interval_summary": [
        "1x 3m27s 152w",
        "2x 9m59s 182w"
      ],
      "intervals": [
        {
          "type": "RECOVERY",
          "duration_secs": 394,
          "avg_power": 124,
          "max_power": 144,
          "avg_hr": 101,
          "max_hr": 114,
          "avg_cadence": 86.03046,
          "zone": 2,
          "training_load": 4.564935,
          "decoupling": -0.6532477
        },
        {
          "type": "WORK",
          "label": "207s@152w95rpm",
          "duration_secs": 207,
          "avg_power": 152,
          "max_power": 162,
          "avg_hr": 116,
          "max_hr": 122,
          "avg_cadence": 94.570045,
          "zone": 3,
          "training_load": 3.556471,
          "decoupling": -1.5612166
        },
        {
          "type": "RECOVERY",
          "duration_secs": 301,
          "avg_power": 109,
          "max_power": 149,
          "avg_hr": 105,
          "max_hr": 126,
          "avg_cadence": 89.62459,
          "zone": 2,
          "training_load": 2.8961325,
          "decoupling": -9.629649
        },
        {
          "type": "WORK",
          "label": "599s@182w94rpm",
          "duration_secs": 598,
          "avg_power": 182,
          "max_power": 184,
          "avg_hr": 127,
          "max_hr": 134,
          "avg_cadence": 93.29933,
          "zone": 4,
          "training_load": 14.762278,
          "decoupling": 6.717715
        },
        {
          "type": "RECOVERY",
          "duration_secs": 302,
          "avg_power": 96,
          "max_power": 182,
          "avg_hr": 110,
          "max_hr": 137,
          "avg_cadence": 84.7649,
          "zone": 1,
          "training_load": 2.508884,
          "decoupling": -15.279204
        },
        {
          "type": "WORK",
          "label": "599s@182w94rpm",
          "duration_secs": 599,
          "avg_power": 182,
          "max_power": 184,
          "avg_hr": 129,
          "max_hr": 139,
          "avg_cadence": 95.2621,
          "zone": 4,
          "training_load": 14.786964,
          "decoupling": 7.7425613
        },
        {
          "type": "RECOVERY",
          "duration_secs": 973,
          "avg_power": 87,
          "max_power": 182,
          "avg_hr": 103,
          "max_hr": 136,
          "avg_cadence": 79.837616,
          "zone": 1,
          "training_load": 6.8984475,
          "decoupling": -8.816854
        }
      ]
    },
    {
      "activity_id": "i139183787",
      "date": "2026-04-12",
      "type": "Swim",
      "name": "Afternoon Swim",
      "interval_summary": [
        "1x 25m 3:16",
        "1x 25m 1:48",
        "2x 75m 1:58",
        "3x 100m 1:55",
        "1x 150m 1:45",
        "3x 150m 1:54",
        "1x 200m 1:56"
      ],
      "intervals": [
        {
          "type": "WORK",
          "label": "49s@86bpm21rpm",
          "duration_secs": 49,
          "avg_hr": 86,
          "max_hr": 89,
          "avg_cadence": 20.571428,
          "zone": 1
        },
        {
          "type": "RECOVERY",
          "duration_secs": 16,
          "avg_hr": 88,
          "max_hr": 89,
          "zone": 1
        },
        {
          "type": "WORK",
          "label": "27s@93bpm24rpm",
          "duration_secs": 27,
          "avg_hr": 93,
          "max_hr": 95,
          "avg_cadence": 24.074074,
          "zone": 1
        },
        {
          "type": "RECOVERY",
          "duration_secs": 20,
          "avg_hr": 91,
          "max_hr": 95,
          "zone": 1
        },
        {
          "type": "WORK",
          "label": "89s@110bpm21rpm",
          "duration_secs": 92,
          "avg_hr": 107,
          "max_hr": 120,
          "avg_cadence": 20.293478,
          "zone": 1
        },
        {
          "type": "RECOVERY",
          "duration_secs": 9,
          "avg_hr": 110,
          "max_hr": 112,
          "zone": 1
        },
        {
          "type": "WORK",
          "label": "89s@110bpm21rpm",
          "duration_secs": 85,
          "avg_hr": 113,
          "max_hr": 120,
          "avg_cadence": 21.494118,
          "zone": 1
        },
        {
          "type": "RECOVERY",
          "duration_secs": 33,
          "avg_hr": 101,
          "max_hr": 112,
          "zone": 1
        },
        {
          "type": "WORK",
          "label": "115s@108bpm20rpm",
          "duration_secs": 114,
          "avg_hr": 108,
          "max_hr": 113,
          "avg_cadence": 21.18421,
          "zone": 1
        },
        {
          "type": "RECOVERY",
          "duration_secs": 19,
          "avg_hr": 112,
          "max_hr": 114,
          "zone": 1
        },
        {
          "type": "WORK",
          "label": "157s@127bpm23rpm",
          "duration_secs": 157,
          "avg_hr": 127,
          "max_hr": 139,
          "avg_cadence": 23.254778,
          "zone": 1
        },
        {
          "type": "RECOVERY",
          "duration_secs": 65,
          "avg_hr": 103,
          "max_hr": 121,
          "zone": 1
        },
        {
          "type": "WORK",
          "label": "115s@108bpm20rpm",
          "duration_secs": 112,
          "avg_hr": 105,
          "max_hr": 125,
          "avg_cadence": 20.142857,
          "zone": 1
        },
        {
          "type": "RECOVERY",
          "duration_secs": 39,
          "avg_hr": 118,
          "max_hr": 126,
          "zone": 1
        },
        {
          "type": "WORK",
          "label": "171s@109bpm22rpm",
          "duration_secs": 166,
          "avg_hr": 113,
          "max_hr": 130,
          "avg_cadence": 20.759037,
          "zone": 1
        },
        {
          "type": "RECOVERY",
          "duration_secs": 81,
          "avg_hr": 99,
          "max_hr": 123,
          "zone": 1
        },
        {
          "type": "WORK",
          "label": "171s@109bpm22rpm",
          "duration_secs": 174,
          "avg_hr": 103,
          "max_hr": 119,
          "avg_cadence": 21.614943,
          "zone": 1
        },
        {
          "type": "RECOVERY",
          "duration_secs": 54,
          "avg_hr": 103,
          "max_hr": 117,
          "zone": 1
        },
        {
          "type": "WORK",
          "label": "115s@108bpm20rpm",
          "duration_secs": 118,
          "avg_hr": 112,
          "max_hr": 130,
          "avg_cadence": 19.728813,
          "zone": 1
        },
        {
          "type": "RECOVERY",
          "duration_secs": 24,
          "avg_hr": 126,
          "max_hr": 131,
          "zone": 1
        },
        {
          "type": "WORK",
          "label": "231s@124bpm23rpm",
          "duration_secs": 231,
          "avg_hr": 124,
          "max_hr": 139,
          "avg_cadence": 22.510822,
          "zone": 1
        },
        {
          "type": "RECOVERY",
          "duration_secs": 46,
          "avg_hr": 109,
          "max_hr": 127,
          "zone": 1
        },
        {
          "type": "WORK",
          "label": "171s@109bpm22rpm",
          "duration_secs": 174,
          "avg_hr": 111,
          "max_hr": 117,
          "avg_cadence": 22.643679,
          "zone": 1
        }
      ]
    },
    {
      "activity_id": "i139069990",
      "date": "2026-04-12",
      "type": "Run",
      "name": "Zone 2 w/ strides",
      "interval_summary": [
        "1x 1h43m 5:31"
      ],
      "intervals": [
        {
          "type": "WORK",
          "label": "6192s@137bpm84rpm",
          "duration_secs": 6192,
          "avg_hr": 137,
          "max_hr": 167,
          "avg_cadence": 84.06224,
          "zone": 1
        }
      ]
    }
  ]
}